instantdl/__init__.py
instantdl/main.py
instantdl/utils.py
instantdl/classification/ResNet50.py
instantdl/classification/__init__.py
instantdl/classification/classification.py
instantdl/classification/imagenet_utils_custom.py
instantdl/data_generator/__init__.py
instantdl/data_generator/auto_evaluation_classification.py
instantdl/data_generator/auto_evaluation_segmentation_regression.py
instantdl/data_generator/data.py
instantdl/data_generator/data_augmentation.py
instantdl/data_generator/data_generator.py
instantdl/data_generator/metrics4losses.py
instantdl/evaluation/Utils_data_evaluation.py
instantdl/evaluation/__init__.py
instantdl/segmentation/InstanceSegmentation.py
instantdl/segmentation/RCNNSettings.py
instantdl/segmentation/RCNNmodel.py
instantdl/segmentation/RegionProposalNetwork.py
instantdl/segmentation/Regression.py
instantdl/segmentation/SemanticSegmentation.py
instantdl/segmentation/UNet_models.py
instantdl/segmentation/__init__.py
instantdl/segmentation/parallel_model_RCNN.py
instantdl/segmentation/utilsRCNN.py
instantdl/segmentation/visualizeRCNN.py
instantdl-1.0.5.dist-info/LICENSE
instantdl-1.0.5.dist-info/METADATA
instantdl-1.0.5.dist-info/WHEEL
instantdl-1.0.5.dist-info/top_level.txt
instantdl-1.0.5.dist-info/RECORD
