Metadata-Version: 2.1
Name: instantdl
Version: 1.0.5
Summary: An easy and convenient Deep Learning pipeline for image segmentation and classification
Home-page: https://github.com/marrlab/InstantDL
Author: Dominik Waibel, Ali Boushehri
Author-email: dominik.waibel@helmholtz-muenchen.de, ali.boushehri@roche.com
License: MIT
Keywords: Computational Biology Deep Learning
Platform: UNKNOWN
Classifier: Development Status :: 3 - Alpha
Classifier: Topic :: Scientific/Engineering :: Image Recognition
Classifier: License :: OSI Approved :: MIT License
Requires-Dist: keras (>=2.2.4)
Requires-Dist: tensorboard (<=1.15.2,>=1.13.0)
